dxlfiletransferclient/__init__.py
dxlfiletransferclient/_version.py
dxlfiletransferclient/client.py
dxlfiletransferclient/constants.py
dxlfiletransferclient/store.py
dxlfiletransferclient/_config/__init__.py
dxlfiletransferclient/_config/sample/__init__.py
dxlfiletransferclient/_config/sample/dxlclient.config
dxlfiletransferclient-0.1.0.dist-info/METADATA
dxlfiletransferclient-0.1.0.dist-info/RECORD
dxlfiletransferclient-0.1.0.dist-info/WHEEL
dxlfiletransferclient-0.1.0.dist-info/top_level.txt
